{
  "pageTitle": "Calculadora de Calorias de Rucking",
  "pageDescription": "Calcule calorias queimadas durante caminhadas com peso (rucking) usando a equação de Pandolf",
  "calculator_inputs": "Entradas da Calculadora",
  "enter_your_details": "Insira seu peso corporal, peso da mochila, ritmo e duração",
  "body_weight": "Peso Corporal",
  "ruck_weight": "Peso da Mochila",
  "kg": "kg",
  "lbs": "lbs",
  "pace": "Ritmo",
  "min_mile": "min/milha",
  "km_h": "km/h",
  "duration": "Duração",
  "minutes": "minutos",
  "hours": "horas",
  "terrain_type": "Tipo de Terreno",
  "flat_pavement": "Pavimento Plano",
  "gravel": "Cascalho",
  "trail": "Trilha",
  "sand": "Areia",
  "grade_optional": "Inclinação/Declive (Opcional)",
  "grade_hint": "Positivo para subida, negativo para descida",
  "calculate": "Calcular",
  "reset": "Redefinir",
  "calories_burned": "Calorias Queimadas",
  "kcal": "kcal",
  "kcal_hr": "kcal/h",
  "enter_details_to_calculate": "Insira seus dados para calcular calorias queimadas",
  "detailed_results": "Resultados Detalhados",
  "calories_summary": "Resumo de Calorias",
  "total_burned": "Total Queimado",
  "per_hour": "Por Hora",
  "metabolic_rate": "Taxa Metabólica",
  "watts": "watts",
  "input_summary": "Resumo de Entrada",
  "load_ratio": "Proporção de Carga",
  "terrain": "Terreno",
  "grade": "Inclinação",
  "calorie_breakdown": "Detalhamento de Calorias",
  "baseline_walking": "Caminhada Base",
  "baseline_desc": "Calorias da caminhada sem carga",
  "ruck_weight_added": "Peso da Mochila Adicionado",
  "ruck_desc": "Calorias adicionais por carregar peso",
  "terrain_grade_effect": "Terreno e Inclinação",
  "terrain_desc": "Efeito do terreno e inclinação",
  "pandolf_equation": "Equação de Pandolf",
  "where": "Onde",
  "body_weight_text": "peso corporal",
  "load_text": "carga",
  "velocity_text": "velocidade",
  "grade_text": "inclinação",
  "terrain_factor_text": "fator de terreno",
  "total_calories": "Calorias Totais"
}
