{
  "company": {
    "name": "Smart Calculators",
    "description": "Su destino preferido para obtener calculadoras en línea gratuitas, precisas y fáciles de usar. Con la confianza de millones de usuarios en todo el mundo.",
    "email": "thesmartcalculators@gmail.com",
    "copyright": "Smart Calculators 2026. Reservados todos los derechos."
  },
  "categories": {
    "title": "Categorías más utilizadas",
    "items": [
      {
        "name": "Calculadoras financieras",
        "href": "/es/financiero"
      },
      {
        "name": "Salud y fitness",
        "href": "/es/salud"
      },
      {
        "name": "Calculadoras matemáticas",
        "href": "/es/matematicas"
      },
      {
        "name": "Calculadoras de física",
        "href": "/es/fisica"
      },
      {
        "name": "Otras calculadoras",
        "href": "/es/otro"
      }
    ]
  },
  "companyLinks": {
    "title": "Empresa",
    "items": [
      {
        "name": "Inicio",
        "href": "/es"
      },
      {
        "name": "Sobre Nosotros",
        "href": "/es/sobre-nosotros"
      },
      {
        "name": "Contáctenos",
        "href": "/es/contacto"
      },
      {
        "name": "Mapa del Sitio",
        "href": "/sitemap"
      },
      {
        "name": "Política Editorial",
        "href": "/editorial-policy-mission-statement"
      },
      {
        "name": "Política de Privacidad",
        "href": "/es/politica-de-privacidad"
      },
      {
        "name": "Términos y Condiciones",
        "href": "/es/terminos-y-condiciones"
      }
    ]
  },
  "allCalculators": {
    "title": "Todas las Calculadoras",
    "showInFooter": true
  },
  "popularCalculators": {
    "title": "Calculadoras Financieras Populares",
    "items": [
      {
        "name": "Calculadora de Hipoteca",
        "href": "https://hypotheken-rechner.net/"
      },
      {
        "name": "Calculadora de Financiamiento",
        "href": "https://hypotheken-rechner.net/finanzierungs-rechner"
      },
      {
        "name": "Calculadora de Financiamiento de Construcción",
        "href": "https://hypotheken-rechner.net/baufinanzierungs-rechner"
      },
      {
        "name": "Calculadora de Presupuesto",
        "href": "https://hypotheken-rechner.net/budget-rechner"
      }
    ]
  },
  "social": {
    "pinterest": "https://www.pinterest.com/thesmartcalculators/",
    "twitter": "https://x.com/SmartCalculat0r",
    "instagram": "https://www.instagram.com/thesmartcalculators/",
    "youtube": "https://www.youtube.com/@TheSmartCalculators"
  }
}